{
	"8ball": {
		"player": "zfk770",
		"playerid": 4805,
		"weight": 0.42,
		"bot": "gofishgame",
		"fishtype": "🎱",
		"fishname": "8ball",
		"catchtype": "normal",
		"chat": "vaiastol",
		"fishid": 269466,
		"chatid": 15255,
		"date": "2026-06-22T16:29:15Z",
		"rank": 66
	},
	"acorn": {
		"player": "vaiastol",
		"playerid": 1135,
		"bot": "gofishgame",
		"fishtype": "🌰",
		"fishname": "acorn",
		"catchtype": "giftwinter",
		"chat": "vaiastol",
		"fishid": 225627,
		"chatid": 10501,
		"date": "2025-12-18T04:22:25Z",
		"rank": 23
	},
	"apple": {
		"player": "hahppyy",
		"playerid": 1310,
		"weight": 1.57,
		"bot": "gofishgame",
		"fishtype": "🍎",
		"fishname": "apple",
		"catchtype": "normal",
		"chat": "vaiastol",
		"fishid": 211841,
		"chatid": 9901,
		"date": "2025-10-31T20:59:46Z",
		"rank": 15
	},
	"balletshoes": {
		"player": "zfk770",
		"playerid": 4805,
		"weight": 0.72,
		"bot": "gofishgame",
		"fishtype": "🩰",
		"fishname": "balletshoes",
		"catchtype": "normal",
		"chat": "vaiastol",
		"fishid": 268113,
		"chatid": 15085,
		"date": "2026-06-16T14:30:12Z",
		"rank": 57
	},
	"bat": {
		"player": "j4song",
		"playerid": 4672,
		"weight": 3.78,
		"bot": "gofishgame",
		"fishtype": "🦇",
		"fishname": "bat",
		"catchtype": "normal",
		"chat": "vaiastol",
		"fishid": 248262,
		"chatid": 12395,
		"date": "2026-03-22T15:45:04Z",
		"rank": 38
	},
	"beaver": {
		"player": "zfk770",
		"playerid": 4805,
		"weight": 4.51,
		"bot": "gofishgame",
		"fishtype": "🦫",
		"fishname": "beaver",
		"catchtype": "normal",
		"chat": "vaiastol",
		"fishid": 271197,
		"chatid": 15494,
		"date": "2026-06-26T23:00:03Z",
		"rank": 96
	},
	"bee": {
		"player": "proswift",
		"playerid": 4151,
		"weight": 0.35,
		"bot": "gofishgame",
		"fishtype": "🐝",
		"fishname": "bee",
		"catchtype": "normal",
		"chat": "vaiastol",
		"fishid": 270575,
		"chatid": 15400,
		"date": "2026-06-24T23:26:42Z",
		"rank": 84
	},
	"bell": {
		"player": "vaiastol",
		"playerid": 1135,
		"bot": "gofishgame",
		"fishtype": "🔔",
		"fishname": "bell",
		"catchtype": "giftbell",
		"chat": "vaiastol",
		"fishid": 223264,
		"chatid": 10400,
		"date": "2025-12-14T22:02:20Z",
		"rank": 20
	},
	"beveragebox": {
		"player": "ichezero",
		"playerid": 4793,
		"weight": 7.21,
		"bot": "gofishgame",
		"fishtype": "🧃",
		"fishname": "beveragebox",
		"catchtype": "normal",
		"chat": "vaiastol",
		"fishid": 270442,
		"chatid": 15377,
		"date": "2026-06-24T18:45:41Z",
		"rank": 79
	},
	"blackcat": {
		"player": "hahppyy",
		"playerid": 1310,
		"weight": 60.23,
		"bot": "gofishgame",
		"fishtype": "🐈‍⬛",
		"fishname": "blackcat",
		"catchtype": "normal",
		"chat": "vaiastol",
		"fishid": 132157,
		"chatid": 2508,
		"date": "2024-12-19T10:38:55Z",
		"rank": 1
	},
	"blowfish": {
		"player": "tharawow",
		"playerid": 4157,
		"weight": 18.25,
		"bot": "gofishgame",
		"fishtype": "🐡",
		"fishname": "blowfish",
		"catchtype": "normal",
		"chat": "vaiastol",
		"fishid": 271276,
		"chatid": 15509,
		"date": "2026-06-27T03:56:17Z",
		"rank": 100
	},
	"bluewhale": {
		"player": "hahppyy",
		"playerid": 1310,
		"weight": 57.28,
		"bot": "gofishgame",
		"fishtype": "🐳",
		"fishname": "bluewhale",
		"catchtype": "normal",
		"chat": "vaiastol",
		"fishid": 269128,
		"chatid": 15211,
		"date": "2026-06-21T15:56:36Z",
		"rank": 64
	},
	"bobacup": {
		"player": "garout",
		"playerid": 3555,
		"weight": 2.74,
		"bot": "gofishgame",
		"fishtype": "🧋",
		"fishname": "bobacup",
		"catchtype": "normal",
		"chat": "vaiastol",
		"fishid": 195824,
		"chatid": 8736,
		"date": "2025-08-28T18:21:29Z",
		"rank": 12
	},
	"bobber": {
		"player": "zfk770",
		"playerid": 4805,
		"bot": "gofishgame",
		"fishtype": "🪀",
		"fishname": "bobber",
		"catchtype": "release",
		"chat": "vaiastol",
		"fishid": 271478,
		"chatid": 15529,
		"date": "2026-06-27T18:21:53Z",
		"rank": 102
	},
	"boot": {
		"player": "obama",
		"playerid": 3655,
		"weight": 1.18,
		"bot": "gofishgame",
		"fishtype": "👢",
		"fishname": "boot",
		"catchtype": "normal",
		"chat": "vaiastol",
		"fishid": 245065,
		"chatid": 12209,
		"date": "2026-03-07T01:15:43Z",
		"rank": 37
	},
	"briefs": {
		"player": "ermnest",
		"playerid": 1484,
		"weight": 5.08,
		"bot": "gofishgame",
		"fishtype": "🩲",
		"fishname": "briefs",
		"catchtype": "normal",
		"chat": "vaiastol",
		"fishid": 270469,
		"chatid": 15380,
		"date": "2026-06-24T19:22:44Z",
		"rank": 80
	},
	"candle": {
		"player": "hahppyy",
		"playerid": 1310,
		"bot": "gofishgame",
		"fishtype": "🕯️",
		"fishname": "candle",
		"catchtype": "releasepumpkin",
		"chat": "vaiastol",
		"fishid": 212662,
		"chatid": 9945,
		"date": "2025-11-03T00:06:45Z",
		"rank": 18
	},
	"candy": {
		"player": "proswift",
		"playerid": 4151,
		"bot": "gofishgame",
		"fishtype": "🍬",
		"fishname": "candy",
		"catchtype": "release",
		"chat": "vaiastol",
		"fishid": 271563,
		"chatid": 15546,
		"date": "2026-06-27T22:57:54Z",
		"rank": 111
	},
	"cannedfood": {
		"player": "thespecialone22",
		"playerid": 4753,
		"weight": 0.23,
		"bot": "gofishgame",
		"fishtype": "🥫",
		"fishname": "cannedfood",
		"catchtype": "normal",
		"chat": "vaiastol",
		"fishid": 249845,
		"chatid": 12522,
		"date": "2026-03-27T03:14:05Z",
		"rank": 39
	},
	"cardinal": {
		"player": "garout",
		"playerid": 3555,
		"weight": 3.99,
		"bot": "gofishgame",
		"fishtype": "🐦",
		"fishname": "cardinal",
		"catchtype": "egg",
		"chat": "vaiastol",
		"fishid": 261513,
		"chatid": 14034,
		"date": "2026-05-11T11:03:53Z",
		"rank": 48
	},
	"caterpillar": {
		"player": "vaiastol",
		"playerid": 1135,
		"weight": 0.27,
		"bot": "gofishgame",
		"fishtype": "🐛",
		"fishname": "caterpillar",
		"catchtype": "normal",
		"chat": "vaiastol",
		"fishid": 271566,
		"chatid": 15548,
		"date": "2026-06-27T23:10:45Z",
		"rank": 113
	},
	"clover": {
		"player": "thespecialone22",
		"playerid": 4753,
		"weight": 2.89,
		"bot": "gofishgame",
		"fishtype": "☘️",
		"fishname": "clover",
		"catchtype": "normal",
		"chat": "vaiastol",
		"fishid": 271516,
		"chatid": 15535,
		"date": "2026-06-27T20:10:45Z",
		"rank": 103
	},
	"cockroach": {
		"player": "ichezero",
		"playerid": 4793,
		"weight": 3.46,
		"bot": "gofishgame",
		"fishtype": "🪳",
		"fishname": "cockroach",
		"catchtype": "normal",
		"chat": "vaiastol",
		"fishid": 269064,
		"chatid": 15202,
		"date": "2026-06-21T11:20:18Z",
		"rank": 63
	},
	"compass": {
		"player": "julialuxel",
		"playerid": 64,
		"verified": true,
		"weight": 7.53,
		"bot": "gofishgame",
		"fishtype": "🧭",
		"fishname": "compass",
		"catchtype": "normal",
		"chat": "vaiastol",
		"fishid": 135383,
		"chatid": 2685,
		"date": "2024-12-25T19:32:21Z",
		"rank": 2
	},
	"cookie": {
		"player": "vaiastol",
		"playerid": 1135,
		"bot": "gofishgame",
		"fishtype": "🍪",
		"fishname": "cookie",
		"catchtype": "giftwinter",
		"chat": "vaiastol",
		"fishid": 225630,
		"chatid": 10504,
		"date": "2025-12-18T04:22:25Z",
		"rank": 23
	},
	"coral": {
		"player": "ayobl7",
		"playerid": 6930,
		"weight": 86.41,
		"bot": "gofishgame",
		"fishtype": "🪸",
		"fishname": "coral",
		"catchtype": "normal",
		"chat": "vaiastol",
		"fishid": 271653,
		"chatid": 15562,
		"date": "2026-06-24T17:17:13Z",
		"rank": 76
	},
	"crab": {
		"player": "ayobl7",
		"playerid": 6930,
		"weight": 0.03,
		"bot": "gofishgame",
		"fishtype": "🦀",
		"fishname": "crab",
		"catchtype": "normal",
		"chat": "vaiastol",
		"fishid": 271223,
		"chatid": 15501,
		"date": "2026-06-27T00:27:27Z",
		"rank": 98
	},
	"crocodile": {
		"player": "ichezero",
		"playerid": 4793,
		"weight": 78.08,
		"bot": "gofishgame",
		"fishtype": "🐊",
		"fishname": "crocodile",
		"catchtype": "normal",
		"chat": "vaiastol",
		"fishid": 270826,
		"chatid": 15433,
		"date": "2026-06-25T20:38:53Z",
		"rank": 87
	},
	"crowberries": {
		"player": "proswift",
		"playerid": 4151,
		"weight": 1,
		"bot": "gofishgame",
		"fishtype": "🍇",
		"fishname": "crowberries",
		"catchtype": "normal",
		"chat": "vaiastol",
		"fishid": 270135,
		"chatid": 15349,
		"date": "2026-06-23T23:59:10Z",
		"rank": 71
	},
	"crown": {
		"player": "ayobl7",
		"playerid": 6930,
		"weight": 63.31,
		"bot": "gofishgame",
		"fishtype": "👑",
		"fishname": "crown",
		"catchtype": "normal",
		"chat": "vaiastol",
		"fishid": 271553,
		"chatid": 15542,
		"date": "2026-06-27T22:22:32Z",
		"rank": 108
	},
	"dagger": {
		"player": "zfk770",
		"playerid": 4805,
		"weight": 47.29,
		"bot": "gofishgame",
		"fishtype": "🗡️",
		"fishname": "dagger",
		"catchtype": "normal",
		"chat": "vaiastol",
		"fishid": 269039,
		"chatid": 15200,
		"date": "2026-06-21T07:34:25Z",
		"rank": 62
	},
	"darksunglasses": {
		"player": "ichezero",
		"playerid": 4793,
		"weight": 9.28,
		"bot": "gofishgame",
		"fishtype": "🕶️",
		"fishname": "darksunglasses",
		"catchtype": "normal",
		"chat": "vaiastol",
		"fishid": 270997,
		"chatid": 15462,
		"date": "2026-06-26T12:52:54Z",
		"rank": 90
	},
	"deadbody": {
		"player": "proswift",
		"playerid": 4151,
		"weight": 18.74,
		"bot": "gofishgame",
		"fishtype": "🧟",
		"fishname": "deadbody",
		"catchtype": "normal",
		"chat": "vaiastol",
		"fishid": 261907,
		"chatid": 14129,
		"date": "2026-05-13T03:16:51Z",
		"rank": 50
	},
	"deadleaves": {
		"player": "proswift",
		"playerid": 4151,
		"weight": 1.27,
		"bot": "gofishgame",
		"fishtype": "🍃",
		"fishname": "deadleaves",
		"catchtype": "normal",
		"chat": "vaiastol",
		"fishid": 257673,
		"chatid": 13384,
		"date": "2026-04-24T17:33:14Z",
		"rank": 43
	},
	"dolphin": {
		"player": "tharawow",
		"playerid": 4157,
		"weight": 27.75,
		"bot": "gofishgame",
		"fishtype": "🐬",
		"fishname": "dolphin",
		"catchtype": "normal",
		"chat": "vaiastol",
		"fishid": 271541,
		"chatid": 15539,
		"date": "2026-06-27T21:39:48Z",
		"rank": 106
	},
	"dragon": {
		"player": "ichezero",
		"playerid": 4793,
		"weight": 173.35,
		"bot": "gofishgame",
		"fishtype": "🐉",
		"fishname": "dragon",
		"catchtype": "normal",
		"chat": "vaiastol",
		"fishid": 270858,
		"chatid": 15442,
		"date": "2026-06-25T23:04:03Z",
		"rank": 88
	},
	"duck": {
		"player": "hahppyy",
		"playerid": 1310,
		"weight": 9.26,
		"bot": "gofishgame",
		"fishtype": "🦆",
		"fishname": "duck",
		"catchtype": "normal",
		"chat": "vaiastol",
		"fishid": 267742,
		"chatid": 15035,
		"date": "2026-06-14T14:31:41Z",
		"rank": 54
	},
	"emptynest": {
		"player": "hahppyy",
		"playerid": 1310,
		"weight": 8.44,
		"bot": "gofishgame",
		"fishtype": "🪹",
		"fishname": "emptynest",
		"catchtype": "normal",
		"chat": "vaiastol",
		"fishid": 271140,
		"chatid": 15480,
		"date": "2026-06-26T19:48:17Z",
		"rank": 95
	},
	"feather": {
		"player": "notsatan13",
		"playerid": 6996,
		"weight": 0.68,
		"bot": "gofishgame",
		"fishtype": "🪶",
		"fishname": "feather",
		"catchtype": "normal",
		"chat": "vaiastol",
		"fishid": 269026,
		"chatid": 15196,
		"date": "2026-06-21T01:43:16Z",
		"rank": 60
	},
	"fish": {
		"player": "zfk770",
		"playerid": 4805,
		"weight": 4.36,
		"bot": "gofishgame",
		"fishtype": "🐟",
		"fishname": "fish",
		"catchtype": "normal",
		"chat": "vaiastol",
		"fishid": 271573,
		"chatid": 15550,
		"date": "2026-06-27T23:30:22Z",
		"rank": 115
	},
	"fly": {
		"player": "hahppyy",
		"playerid": 1310,
		"weight": 0.19,
		"bot": "gofishgame",
		"fishtype": "🪰",
		"fishname": "fly",
		"catchtype": "normal",
		"chat": "vaiastol",
		"fishid": 270790,
		"chatid": 15425,
		"date": "2026-06-25T18:40:21Z",
		"rank": 86
	},
	"frog": {
		"player": "vaiastol",
		"playerid": 1135,
		"weight": 2.72,
		"bot": "gofishgame",
		"fishtype": "🐸",
		"fishname": "frog",
		"catchtype": "normal",
		"chat": "vaiastol",
		"fishid": 271454,
		"chatid": 15527,
		"date": "2026-06-27T17:12:29Z",
		"rank": 101
	},
	"genie": {
		"player": "wcd0",
		"playerid": 2360,
		"weight": 119.98,
		"bot": "gofishgame",
		"fishtype": "🧞‍♂️",
		"fishname": "genie",
		"catchtype": "normal",
		"chat": "vaiastol",
		"fishid": 212198,
		"chatid": 9921,
		"date": "2025-11-01T20:23:46Z",
		"rank": 16
	},
	"gloves": {
		"player": "proswift",
		"playerid": 4151,
		"weight": 0.61,
		"bot": "gofishgame",
		"fishtype": "🧤",
		"fishname": "gloves",
		"catchtype": "normal",
		"chat": "vaiastol",
		"fishid": 238333,
		"chatid": 11653,
		"date": "2026-02-03T15:27:48Z",
		"rank": 32
	},
	"goose": {
		"player": "vaiastol",
		"playerid": 1135,
		"weight": 2.05,
		"bot": "gofishgame",
		"fishtype": "🪿",
		"fishname": "goose",
		"catchtype": "egg",
		"chat": "vaiastol",
		"fishid": 240657,
		"chatid": 11910,
		"date": "2026-02-13T19:22:51Z",
		"rank": 35
	},
	"grass": {
		"player": "proswift",
		"playerid": 4151,
		"weight": 0.17,
		"bot": "gofishgame",
		"fishtype": "🌾",
		"fishname": "grass",
		"catchtype": "normal",
		"chat": "vaiastol",
		"fishid": 257982,
		"chatid": 13425,
		"date": "2026-04-25T23:35:17Z",
		"rank": 45
	},
	"hat": {
		"player": "zfk770",
		"playerid": 4805,
		"weight": 6.18,
		"bot": "gofishgame",
		"fishtype": "👒",
		"fishname": "hat",
		"catchtype": "normal",
		"chat": "vaiastol",
		"fishid": 268012,
		"chatid": 15067,
		"date": "2026-06-15T21:07:24Z",
		"rank": 55
	},
	"hook": {
		"player": "vaiastol",
		"playerid": 1135,
		"bot": "gofishgame",
		"fishtype": "🪝",
		"fishname": "hook",
		"catchtype": "release",
		"chat": "vaiastol",
		"fishid": 271119,
		"chatid": 15476,
		"date": "2026-06-26T18:42:22Z",
		"rank": 94
	},
	"icecube": {
		"player": "ryakarr",
		"playerid": 4153,
		"weight": 9.46,
		"bot": "gofishgame",
		"fishtype": "🧊",
		"fishname": "icecube",
		"catchtype": "normal",
		"chat": "vaiastol",
		"fishid": 251029,
		"chatid": 12627,
		"date": "2026-03-31T07:37:11Z",
		"rank": 40
	},
	"icesaw": {
		"player": "vaiastol",
		"playerid": 1135,
		"weight": 0.68,
		"bot": "gofishgame",
		"fishtype": "🪚",
		"fishname": "icesaw",
		"catchtype": "normal",
		"chat": "vaiastol",
		"fishid": 142997,
		"chatid": 3672,
		"date": "2025-01-22T04:04:09Z",
		"rank": 5
	},
	"iceskate": {
		"player": "vaiastol",
		"playerid": 1135,
		"weight": 1.36,
		"bot": "gofishgame",
		"fishtype": "⛸️",
		"fishname": "iceskate",
		"catchtype": "normal",
		"chat": "vaiastol",
		"fishid": 142956,
		"chatid": 3663,
		"date": "2025-01-21T23:03:12Z",
		"rank": 4
	},
	"iphone": {
		"player": "notsatan13",
		"playerid": 6996,
		"weight": 0.76,
		"bot": "gofishgame",
		"fishtype": "📱",
		"fishname": "iphone",
		"catchtype": "normal",
		"chat": "vaiastol",
		"fishid": 270334,
		"chatid": 15369,
		"date": "2026-06-24T12:51:07Z",
		"rank": 75
	},
	"jar": {
		"player": "vaiastol",
		"playerid": 1135,
		"bot": "gofishgame",
		"fishtype": "🫙",
		"fishname": "jar",
		"catchtype": "sonnythrow",
		"chat": "vaiastol",
		"fishid": 270541,
		"chatid": 15392,
		"date": "2026-06-24T21:42:00Z",
		"rank": 82
	},
	"jellyfish": {
		"player": "tharawow",
		"playerid": 4157,
		"weight": 7.82,
		"bot": "gofishgame",
		"fishtype": "🪼",
		"fishname": "jellyfish",
		"catchtype": "normal",
		"chat": "vaiastol",
		"fishid": 270205,
		"chatid": 15359,
		"date": "2026-06-24T04:39:30Z",
		"rank": 73
	},
	"kite": {
		"player": "garout",
		"playerid": 3555,
		"weight": 8.74,
		"bot": "gofishgame",
		"fishtype": "🪁",
		"fishname": "kite",
		"catchtype": "normal",
		"chat": "vaiastol",
		"fishid": 192002,
		"chatid": 8506,
		"date": "2025-08-06T23:32:14Z",
		"rank": 11
	},
	"leaf": {
		"player": "gstaman911",
		"playerid": 3529,
		"weight": 0.94,
		"bot": "gofishgame",
		"fishtype": "🍁",
		"fishname": "leaf",
		"catchtype": "normal",
		"chat": "vaiastol",
		"fishid": 215123,
		"chatid": 10043,
		"date": "2025-11-12T05:36:34Z",
		"rank": 19
	},
	"letter": {
		"player": "vaiastol",
		"playerid": 1135,
		"bot": "gofishgame",
		"fishtype": "✉️",
		"fishname": "letter",
		"catchtype": "giftwinter",
		"chat": "vaiastol",
		"fishid": 225632,
		"chatid": 10506,
		"date": "2025-12-18T04:22:25Z",
		"rank": 23
	},
	"lizard": {
		"player": "proswift",
		"playerid": 4151,
		"weight": 4.19,
		"bot": "gofishgame",
		"fishtype": "🦎",
		"fishname": "lizard",
		"catchtype": "normal",
		"chat": "vaiastol",
		"fishid": 271562,
		"chatid": 15545,
		"date": "2026-06-27T22:57:04Z",
		"rank": 110
	},
	"lobster": {
		"player": "ayobl7",
		"playerid": 6930,
		"weight": 105.24,
		"bot": "gofishgame",
		"fishtype": "🦞",
		"fishname": "lobster",
		"catchtype": "normal",
		"chat": "vaiastol",
		"fishid": 271522,
		"chatid": 15536,
		"date": "2026-06-27T20:28:09Z",
		"rank": 104
	},
	"log": {
		"player": "zfk770",
		"playerid": 4805,
		"weight": 15.15,
		"bot": "gofishgame",
		"fishtype": "🪵",
		"fishname": "log",
		"catchtype": "normal",
		"chat": "vaiastol",
		"fishid": 261623,
		"chatid": 14059,
		"date": "2026-05-11T18:51:42Z",
		"rank": 49
	},
	"lupine": {
		"player": "garout",
		"playerid": 3555,
		"weight": 1.18,
		"bot": "gofishgame",
		"fishtype": "🪻",
		"fishname": "lupine",
		"catchtype": "normal",
		"chat": "vaiastol",
		"fishid": 190924,
		"chatid": 8462,
		"date": "2025-07-31T12:27:05Z",
		"rank": 10
	},
	"lure": {
		"player": "ichezero",
		"playerid": 4793,
		"weight": 1.22,
		"bot": "gofishgame",
		"fishtype": "🎏",
		"fishname": "lure",
		"catchtype": "normal",
		"chat": "vaiastol",
		"fishid": 271090,
		"chatid": 15474,
		"date": "2026-06-26T17:11:51Z",
		"rank": 92
	},
	"mermaid": {
		"player": "thespecialone22",
		"playerid": 4753,
		"weight": 138.32,
		"bot": "gofishgame",
		"fishtype": "🧜‍♀️",
		"fishname": "mermaid",
		"catchtype": "normal",
		"chat": "vaiastol",
		"fishid": 257759,
		"chatid": 13392,
		"date": "2026-04-24T23:55:40Z",
		"rank": 44
	},
	"moose": {
		"player": "proswift",
		"playerid": 4151,
		"weight": 75.63,
		"bot": "gofishgame",
		"fishtype": "🫎",
		"fishname": "moose",
		"catchtype": "normal",
		"chat": "vaiastol",
		"fishid": 256618,
		"chatid": 13223,
		"date": "2026-04-20T15:56:28Z",
		"rank": 42
	},
	"mosquito": {
		"player": "hahppyy",
		"playerid": 1310,
		"weight": 0.06,
		"bot": "gofishgame",
		"fishtype": "🦟",
		"fishname": "mosquito",
		"catchtype": "normal",
		"chat": "vaiastol",
		"fishid": 196676,
		"chatid": 8800,
		"date": "2025-08-31T20:32:34Z",
		"rank": 13
	},
	"mushroom": {
		"player": "proswift",
		"playerid": 4151,
		"weight": 6.6,
		"bot": "gofishgame",
		"fishtype": "🍄‍🟫",
		"fishname": "mushroom",
		"catchtype": "normal",
		"chat": "vaiastol",
		"fishid": 259517,
		"chatid": 13640,
		"date": "2026-04-29T22:54:24Z",
		"rank": 46
	},
	"nestwitheggs": {
		"player": "thespecialone22",
		"playerid": 4753,
		"weight": 6.27,
		"bot": "gofishgame",
		"fishtype": "🪺",
		"fishname": "nestwitheggs",
		"catchtype": "normal",
		"chat": "vaiastol",
		"fishid": 270160,
		"chatid": 15354,
		"date": "2026-06-24T01:25:08Z",
		"rank": 72
	},
	"oceanplant": {
		"player": "ryakarr",
		"playerid": 4153,
		"weight": 0.39,
		"bot": "gofishgame",
		"fishtype": "🍄",
		"fishname": "oceanplant",
		"catchtype": "normal",
		"chat": "vaiastol",
		"fishid": 233260,
		"chatid": 11201,
		"date": "2026-01-13T11:40:42Z",
		"rank": 29
	},
	"octopus": {
		"player": "tharawow",
		"playerid": 4157,
		"weight": 44.98,
		"bot": "gofishgame",
		"fishtype": "🐙",
		"fishname": "octopus",
		"catchtype": "normal",
		"chat": "vaiastol",
		"fishid": 270922,
		"chatid": 15456,
		"date": "2026-06-26T03:39:32Z",
		"rank": 89
	},
	"oildrum": {
		"player": "julialuxel",
		"playerid": 64,
		"verified": true,
		"weight": 62.96,
		"bot": "gofishgame",
		"fishtype": "🛢️",
		"fishname": "oildrum",
		"catchtype": "normal",
		"chat": "vaiastol",
		"fishid": 188195,
		"chatid": 8226,
		"date": "2025-07-18T02:56:55Z",
		"rank": 9
	},
	"otter": {
		"player": "ryakarr",
		"playerid": 4153,
		"weight": 6.9,
		"bot": "gofishgame",
		"fishtype": "🦦",
		"fishname": "otter",
		"catchtype": "normal",
		"chat": "vaiastol",
		"fishid": 251055,
		"chatid": 12629,
		"date": "2026-03-31T10:12:47Z",
		"rank": 41
	},
	"owl": {
		"player": "respirate_",
		"playerid": 2525,
		"weight": 2.08,
		"bot": "gofishgame",
		"fishtype": "🦉",
		"fishname": "owl",
		"catchtype": "egg",
		"chat": "vaiastol",
		"fishid": 231535,
		"chatid": 11029,
		"date": "2026-01-05T08:05:41Z",
		"rank": 28
	},
	"oyster": {
		"player": "thespecialone22",
		"playerid": 4753,
		"weight": 15.13,
		"bot": "gofishgame",
		"fishtype": "🦪",
		"fishname": "oyster",
		"catchtype": "normal",
		"chat": "vaiastol",
		"fishid": 269030,
		"chatid": 15199,
		"date": "2026-06-21T02:05:05Z",
		"rank": 61
	},
	"penguin": {
		"player": "hahppyy",
		"playerid": 1310,
		"weight": 32.32,
		"bot": "gofishgame",
		"fishtype": "🐧",
		"fishname": "penguin",
		"catchtype": "normal",
		"chat": "vaiastol",
		"fishid": 143122,
		"chatid": 3682,
		"date": "2025-01-22T23:43:51Z",
		"rank": 6
	},
	"plankton": {
		"player": "yoimlee",
		"playerid": 785,
		"weight": 6.48,
		"bot": "gofishgame",
		"fishtype": "🦠",
		"fishname": "plankton",
		"catchtype": "normal",
		"chat": "vaiastol",
		"fishid": 236167,
		"chatid": 11461,
		"date": "2026-01-25T06:54:35Z",
		"rank": 31
	},
	"polarbear": {
		"player": "vaiastol",
		"playerid": 1135,
		"weight": 61.51,
		"bot": "gofishgame",
		"fishtype": "🐻‍❄️",
		"fishname": "polarbear",
		"catchtype": "normal",
		"chat": "vaiastol",
		"fishid": 137826,
		"chatid": 3020,
		"date": "2025-01-01T21:13:46Z",
		"rank": 3
	},
	"present": {
		"player": "vaiastol",
		"playerid": 1135,
		"bot": "gofishgame",
		"fishtype": "🎁",
		"fishname": "present",
		"catchtype": "giftpresent",
		"chat": "vaiastol",
		"fishid": 223409,
		"chatid": 10409,
		"date": "2025-12-15T08:12:25Z",
		"rank": 21
	},
	"pumpkin": {
		"player": "hahppyy",
		"playerid": 1310,
		"weight": 8.35,
		"bot": "gofishgame",
		"fishtype": "🎃",
		"fishname": "pumpkin",
		"catchtype": "normal",
		"chat": "vaiastol",
		"fishid": 212661,
		"chatid": 9944,
		"date": "2025-11-03T00:06:38Z",
		"rank": 17
	},
	"robin": {
		"player": "vaiastol",
		"playerid": 1135,
		"weight": 0.33,
		"bot": "gofishgame",
		"fishtype": "🐦‍⬛",
		"fishname": "robin",
		"catchtype": "egg",
		"chat": "vaiastol",
		"fishid": 268315,
		"chatid": 15115,
		"date": "2026-06-17T14:30:21Z",
		"rank": 59
	},
	"rock": {
		"player": "ichezero",
		"playerid": 4793,
		"weight": 12.15,
		"bot": "gofishgame",
		"fishtype": "🪨",
		"fishname": "rock",
		"catchtype": "normal",
		"chat": "vaiastol",
		"fishid": 267058,
		"chatid": 14965,
		"date": "2026-06-11T12:13:50Z",
		"rank": 53
	},
	"rose": {
		"player": "gstaman911",
		"playerid": 3529,
		"weight": 1.21,
		"bot": "gofishgame",
		"fishtype": "🌹",
		"fishname": "rose",
		"catchtype": "normal",
		"chat": "vaiastol",
		"fishid": 209098,
		"chatid": 9731,
		"date": "2025-10-20T11:04:26Z",
		"rank": 14
	},
	"sandal": {
		"player": "proswift",
		"playerid": 4151,
		"weight": 0.32,
		"bot": "gofishgame",
		"fishtype": "👡",
		"fishname": "sandal",
		"catchtype": "normal",
		"chat": "vaiastol",
		"fishid": 259738,
		"chatid": 13666,
		"date": "2026-04-30T20:28:18Z",
		"rank": 47
	},
	"sandwich": {
		"player": "zfk770",
		"playerid": 4805,
		"weight": 0.35,
		"bot": "gofishgame",
		"fishtype": "🥪",
		"fishname": "sandwich",
		"catchtype": "normal",
		"chat": "vaiastol",
		"fishid": 268146,
		"chatid": 15088,
		"date": "2026-06-16T16:22:02Z",
		"rank": 58
	},
	"sauropod": {
		"player": "ayobl7",
		"playerid": 6930,
		"weight": 160.41,
		"bot": "gofishgame",
		"fishtype": "🦕",
		"fishname": "sauropod",
		"catchtype": "normal",
		"chat": "vaiastol",
		"fishid": 269197,
		"chatid": 15224,
		"date": "2026-06-21T20:16:36Z",
		"rank": 65
	},
	"seacucumber": {
		"player": "ichezero",
		"playerid": 4793,
		"weight": 7.02,
		"bot": "gofishgame",
		"fishtype": "🥒",
		"fishname": "seacucumber",
		"catchtype": "normal",
		"chat": "vaiastol",
		"fishid": 271657,
		"chatid": 15566,
		"date": "2026-06-24T17:45:26Z",
		"rank": 77
	},
	"seal": {
		"player": "j4song",
		"playerid": 4672,
		"weight": 11.85,
		"bot": "gofishgame",
		"fishtype": "🦭",
		"fishname": "seal",
		"catchtype": "normal",
		"chat": "vaiastol",
		"fishid": 238584,
		"chatid": 11682,
		"date": "2026-02-04T15:13:37Z",
		"rank": 33
	},
	"seaweed": {
		"player": "zfk770",
		"playerid": 4805,
		"weight": 0.64,
		"bot": "gofishgame",
		"fishtype": "🌿",
		"fishname": "seaweed",
		"catchtype": "normal",
		"chat": "vaiastol",
		"fishid": 271545,
		"chatid": 15541,
		"date": "2026-06-27T21:45:16Z",
		"rank": 107
	},
	"shark": {
		"player": "ichezero",
		"playerid": 4793,
		"weight": 4.34,
		"bot": "gofishgame",
		"fishtype": "🦈",
		"fishname": "shark",
		"catchtype": "normal",
		"chat": "vaiastol",
		"fishid": 270552,
		"chatid": 15394,
		"date": "2026-06-24T22:02:14Z",
		"rank": 83
	},
	"shell": {
		"player": "ichezero",
		"playerid": 4793,
		"weight": 2.01,
		"bot": "gofishgame",
		"fishtype": "🐚",
		"fishname": "shell",
		"catchtype": "normal",
		"chat": "vaiastol",
		"fishid": 271668,
		"chatid": 15577,
		"date": "2026-06-25T15:33:12Z",
		"rank": 85
	},
	"shoppingcart": {
		"player": "vaiastol",
		"playerid": 1135,
		"weight": 26.51,
		"bot": "gofishgame",
		"fishtype": "🛒",
		"fishname": "shoppingcart",
		"catchtype": "normal",
		"chat": "vaiastol",
		"fishid": 151921,
		"chatid": 4620,
		"date": "2025-03-02T19:49:40Z",
		"rank": 7
	},
	"shrimp": {
		"player": "thespecialone22",
		"playerid": 4753,
		"weight": 5.3,
		"bot": "gofishgame",
		"fishtype": "🦐",
		"fishname": "shrimp",
		"catchtype": "normal",
		"chat": "vaiastol",
		"fishid": 271274,
		"chatid": 15508,
		"date": "2026-06-27T03:37:34Z",
		"rank": 99
	},
	"skull": {
		"player": "ichezero",
		"playerid": 4793,
		"weight": 0.64,
		"bot": "gofishgame",
		"fishtype": "💀",
		"fishname": "skull",
		"catchtype": "normal",
		"chat": "vaiastol",
		"fishid": 269829,
		"chatid": 15299,
		"date": "2026-06-23T10:12:35Z",
		"rank": 67
	},
	"slotmachine": {
		"player": "ryakarr",
		"playerid": 4153,
		"bot": "gofishgame",
		"fishtype": "🎰",
		"fishname": "slotmachine",
		"catchtype": "release",
		"chat": "vaiastol",
		"fishid": 266358,
		"chatid": 14860,
		"date": "2026-06-07T06:04:48Z",
		"rank": 52
	},
	"snail": {
		"player": "proswift",
		"playerid": 4151,
		"weight": 0.97,
		"bot": "gofishgame",
		"fishtype": "🐌",
		"fishname": "snail",
		"catchtype": "normal",
		"chat": "vaiastol",
		"fishid": 271572,
		"chatid": 15549,
		"date": "2026-06-27T23:29:10Z",
		"rank": 114
	},
	"snake": {
		"player": "zfk770",
		"playerid": 4805,
		"weight": 1.39,
		"bot": "gofishgame",
		"fishtype": "🐍",
		"fishname": "snake",
		"catchtype": "normal",
		"chat": "vaiastol",
		"fishid": 271556,
		"chatid": 15544,
		"date": "2026-06-27T22:34:19Z",
		"rank": 109
	},
	"sneaker": {
		"player": "luvwiiseat",
		"playerid": 3784,
		"weight": 1.99,
		"bot": "gofishgame",
		"fishtype": "👟",
		"fishname": "sneaker",
		"catchtype": "normal",
		"chat": "vaiastol",
		"fishid": 176144,
		"chatid": 7412,
		"date": "2025-05-27T00:29:20Z",
		"rank": 8
	},
	"socks": {
		"player": "tharawow",
		"playerid": 4157,
		"weight": 0.73,
		"bot": "gofishgame",
		"fishtype": "🧦",
		"fishname": "socks",
		"catchtype": "normal",
		"chat": "vaiastol",
		"fishid": 270044,
		"chatid": 15335,
		"date": "2026-06-23T19:29:34Z",
		"rank": 70
	},
	"spider": {
		"player": "ichezero",
		"playerid": 4793,
		"weight": 1.91,
		"bot": "gofishgame",
		"fishtype": "🕷️",
		"fishname": "spider",
		"catchtype": "normal",
		"chat": "vaiastol",
		"fishid": 270485,
		"chatid": 15381,
		"date": "2026-06-24T19:59:01Z",
		"rank": 81
	},
	"spiderweb": {
		"player": "zfk770",
		"playerid": 4805,
		"weight": 0.05,
		"bot": "gofishgame",
		"fishtype": "🕸️",
		"fishname": "spiderweb",
		"catchtype": "normal",
		"chat": "vaiastol",
		"fishid": 269875,
		"chatid": 15305,
		"date": "2026-06-23T12:35:06Z",
		"rank": 69
	},
	"sponge": {
		"player": "ayobl7",
		"playerid": 6930,
		"weight": 17.32,
		"bot": "gofishgame",
		"fishtype": "🧽",
		"fishname": "sponge",
		"catchtype": "normal",
		"chat": "vaiastol",
		"fishid": 271113,
		"chatid": 15475,
		"date": "2026-06-26T18:27:00Z",
		"rank": 93
	},
	"squid": {
		"player": "ermnest",
		"playerid": 1484,
		"weight": 59.41,
		"bot": "gofishgame",
		"fishtype": "🦑",
		"fishname": "squid",
		"catchtype": "normal",
		"chat": "vaiastol",
		"fishid": 271218,
		"chatid": 15500,
		"date": "2026-06-27T00:13:41Z",
		"rank": 97
	},
	"squirrel": {
		"player": "garout",
		"playerid": 3555,
		"bot": "gofishgame",
		"fishtype": "🐿️",
		"fishname": "squirrel",
		"catchtype": "squirrel",
		"chat": "vaiastol",
		"fishid": 223639,
		"chatid": 10415,
		"date": "2025-12-15T19:10:04Z",
		"rank": 22
	},
	"sunflower": {
		"player": "zfk770",
		"playerid": 4805,
		"weight": 1.51,
		"bot": "gofishgame",
		"fishtype": "🌻",
		"fishname": "sunflower",
		"catchtype": "normal",
		"chat": "vaiastol",
		"fishid": 271535,
		"chatid": 15537,
		"date": "2026-06-27T21:09:47Z",
		"rank": 105
	},
	"swan": {
		"player": "vaiastol",
		"playerid": 1135,
		"weight": 2.9,
		"bot": "gofishgame",
		"fishtype": "🦢",
		"fishname": "swan",
		"catchtype": "egg",
		"chat": "vaiastol",
		"fishid": 228689,
		"chatid": 10766,
		"date": "2025-12-27T04:57:00Z",
		"rank": 27
	},
	"teddybear": {
		"player": "ryakarr",
		"playerid": 4153,
		"weight": 3.7,
		"bot": "gofishgame",
		"fishtype": "🧸",
		"fishname": "teddybear",
		"catchtype": "normal",
		"chat": "vaiastol",
		"fishid": 235361,
		"chatid": 11385,
		"date": "2026-01-21T17:41:38Z",
		"rank": 30
	},
	"thongsandal": {
		"player": "ayobl7",
		"playerid": 6930,
		"weight": 0.91,
		"bot": "gofishgame",
		"fishtype": "🩴",
		"fishname": "thongsandal",
		"catchtype": "normal",
		"chat": "vaiastol",
		"fishid": 270436,
		"chatid": 15376,
		"date": "2026-06-24T18:26:30Z",
		"rank": 78
	},
	"tropicalfish": {
		"player": "ichezero",
		"playerid": 4793,
		"weight": 3.43,
		"bot": "gofishgame",
		"fishtype": "🐠",
		"fishname": "tropicalfish",
		"catchtype": "normal",
		"chat": "vaiastol",
		"fishid": 271065,
		"chatid": 15468,
		"date": "2026-06-26T16:29:29Z",
		"rank": 91
	},
	"tulip": {
		"player": "garout",
		"playerid": 3555,
		"weight": 1.96,
		"bot": "gofishgame",
		"fishtype": "🌷",
		"fishname": "tulip",
		"catchtype": "normal",
		"chat": "vaiastol",
		"fishid": 265286,
		"chatid": 14729,
		"date": "2026-05-28T08:33:41Z",
		"rank": 51
	},
	"turtle": {
		"player": "notsatan13",
		"playerid": 6996,
		"weight": 47.8,
		"bot": "gofishgame",
		"fishtype": "🐢",
		"fishname": "turtle",
		"catchtype": "normal",
		"chat": "vaiastol",
		"fishid": 271564,
		"chatid": 15547,
		"date": "2026-06-27T23:08:49Z",
		"rank": 112
	},
	"umbrella": {
		"player": "yoimlee",
		"playerid": 785,
		"weight": 1.52,
		"bot": "gofishgame",
		"fishtype": "☂️",
		"fishname": "umbrella",
		"catchtype": "normal",
		"chat": "vaiastol",
		"fishid": 268103,
		"chatid": 15083,
		"date": "2026-06-16T13:45:12Z",
		"rank": 56
	},
	"whale": {
		"player": "tharawow",
		"playerid": 4157,
		"weight": 51.49,
		"bot": "gofishgame",
		"fishtype": "🐋",
		"fishname": "whale",
		"catchtype": "normal",
		"chat": "vaiastol",
		"fishid": 269831,
		"chatid": 15300,
		"date": "2026-06-23T10:24:46Z",
		"rank": 68
	},
	"wiltedflower": {
		"player": "garout",
		"playerid": 3555,
		"weight": 1.88,
		"bot": "gofishgame",
		"fishtype": "🥀",
		"fishname": "wiltedflower",
		"catchtype": "normal",
		"chat": "vaiastol",
		"fishid": 240158,
		"chatid": 11863,
		"date": "2026-02-11T13:58:37Z",
		"rank": 34
	},
	"wireline": {
		"player": "notsatan13",
		"playerid": 6996,
		"weight": 0.35,
		"bot": "gofishgame",
		"fishtype": "🧵",
		"fishname": "wireline",
		"catchtype": "normal",
		"chat": "vaiastol",
		"fishid": 270318,
		"chatid": 15365,
		"date": "2026-06-24T12:07:56Z",
		"rank": 74
	},
	"worm": {
		"player": "leastsussyimposter",
		"playerid": 1353,
		"weight": 9.67,
		"bot": "gofishgame",
		"fishtype": "🪱",
		"fishname": "worm",
		"catchtype": "normal",
		"chat": "vaiastol",
		"fishid": 243770,
		"chatid": 12105,
		"date": "2026-02-28T19:40:11Z",
		"rank": 36
	},
	"wrappingpaper": {
		"player": "vaiastol",
		"playerid": 1135,
		"bot": "gofishgame",
		"fishtype": "🎀",
		"fishname": "wrappingpaper",
		"catchtype": "giftwinter",
		"chat": "vaiastol",
		"fishid": 225628,
		"chatid": 10502,
		"date": "2025-12-18T04:22:25Z",
		"rank": 23
	}
}