{
	"8ball": {
		"player": "kohrro",
		"playerid": 2887,
		"weight": 8.57,
		"bot": "gofishgame",
		"fishtype": "🎱",
		"fishname": "8ball",
		"catchtype": "normal",
		"chat": "d_egree",
		"fishid": 154386,
		"chatid": 257,
		"date": "2025-03-13T10:05:29Z",
		"rank": 26
	},
	"acorn": {
		"player": "kohrro",
		"playerid": 2887,
		"weight": 2.94,
		"bot": "gofishgame",
		"fishtype": "🌰",
		"fishname": "acorn",
		"catchtype": "normal",
		"chat": "d_egree",
		"fishid": 104835,
		"chatid": 124,
		"date": "2024-09-29T17:10:00Z",
		"rank": 39
	},
	"balletshoes": {
		"player": "islcfc",
		"playerid": 63,
		"weight": 1.5,
		"bot": "gofishgame",
		"fishtype": "🩰",
		"fishname": "balletshoes",
		"catchtype": "normal",
		"chat": "d_egree",
		"fishid": 163815,
		"chatid": 279,
		"date": "2023-12-07T21:39:35Z",
		"rank": 47
	},
	"bee": {
		"player": "kohrro",
		"playerid": 2887,
		"weight": 0.02,
		"bot": "gofishgame",
		"fishtype": "🐝",
		"fishname": "bee",
		"catchtype": "normal",
		"chat": "d_egree",
		"fishid": 196362,
		"chatid": 306,
		"date": "2025-08-30T18:04:31Z",
		"rank": 58
	},
	"beveragebox": {
		"player": "ouacewi",
		"playerid": 79,
		"verified": true,
		"weight": 4.2,
		"bot": "gofishgame",
		"fishtype": "🧃",
		"fishname": "beveragebox",
		"catchtype": "normal",
		"chat": "d_egree",
		"fishid": 163754,
		"chatid": 271,
		"date": "2023-09-26T20:27:31Z",
		"rank": 36
	},
	"blowfish": {
		"player": "kohrro",
		"playerid": 2887,
		"weight": 23.13,
		"bot": "gofishgame",
		"fishtype": "🐡",
		"fishname": "blowfish",
		"catchtype": "normal",
		"chat": "d_egree",
		"fishid": 102501,
		"chatid": 89,
		"date": "2024-09-21T19:04:29Z",
		"rank": 17
	},
	"bobber": {
		"player": "kohrro",
		"playerid": 2887,
		"weight": 7.41,
		"bot": "gofishgame",
		"fishtype": "🪀",
		"fishname": "bobber",
		"catchtype": "normal",
		"chat": "d_egree",
		"fishid": 103824,
		"chatid": 100,
		"date": "2024-09-26T20:19:46Z",
		"rank": 30
	},
	"boot": {
		"player": "benni900",
		"playerid": 228,
		"weight": 0.25,
		"bot": "gofishgame",
		"fishtype": "👢",
		"fishname": "boot",
		"catchtype": "normal",
		"chat": "d_egree",
		"fishid": 148134,
		"chatid": 187,
		"date": "2025-02-16T12:11:25Z",
		"rank": 57
	},
	"cannedfood": {
		"player": "benni900",
		"playerid": 228,
		"weight": 1.13,
		"bot": "gofishgame",
		"fishtype": "🥫",
		"fishname": "cannedfood",
		"catchtype": "normal",
		"chat": "d_egree",
		"fishid": 149718,
		"chatid": 247,
		"date": "2025-02-24T14:01:06Z",
		"rank": 50
	},
	"caterpillar": {
		"player": "kohrro",
		"playerid": 2887,
		"weight": 0.81,
		"bot": "gofishgame",
		"fishtype": "🐛",
		"fishname": "caterpillar",
		"catchtype": "normal",
		"chat": "d_egree",
		"fishid": 196340,
		"chatid": 304,
		"date": "2025-08-30T15:54:03Z",
		"rank": 52
	},
	"cockroach": {
		"player": "benni900",
		"playerid": 228,
		"weight": 20.87,
		"bot": "gofishgame",
		"fishtype": "🪳",
		"fishname": "cockroach",
		"catchtype": "normal",
		"chat": "d_egree",
		"fishid": 148160,
		"chatid": 190,
		"date": "2025-02-16T15:06:42Z",
		"rank": 20
	},
	"coral": {
		"player": "kohrro",
		"playerid": 2887,
		"weight": 47.35,
		"bot": "gofishgame",
		"fishtype": "🪸",
		"fishname": "coral",
		"catchtype": "normal",
		"chat": "d_egree",
		"fishid": 99205,
		"chatid": 22,
		"date": "2024-09-03T12:55:38Z",
		"rank": 13
	},
	"crab": {
		"player": "benni900",
		"playerid": 228,
		"weight": 2.69,
		"bot": "gofishgame",
		"fishtype": "🦀",
		"fishname": "crab",
		"catchtype": "normal",
		"chat": "d_egree",
		"fishid": 149529,
		"chatid": 239,
		"date": "2025-02-23T12:22:57Z",
		"rank": 40
	},
	"crocodile": {
		"player": "kohrro",
		"playerid": 2887,
		"weight": 132.02,
		"bot": "gofishgame",
		"fishtype": "🐊",
		"fishname": "crocodile",
		"catchtype": "normal",
		"chat": "d_egree",
		"fishid": 106266,
		"chatid": 144,
		"date": "2024-10-03T16:47:23Z",
		"rank": 2
	},
	"cucumber": {
		"player": "kohrro",
		"playerid": 2887,
		"weight": 6.47,
		"bot": "gofishgame",
		"fishtype": "🥒",
		"fishname": "cucumber",
		"catchtype": "normal",
		"chat": "d_egree",
		"fishid": 101498,
		"chatid": 59,
		"date": "2024-09-15T15:03:32Z",
		"rank": 32
	},
	"dagger": {
		"player": "kohrro",
		"playerid": 2887,
		"weight": 13.93,
		"bot": "gofishgame",
		"fishtype": "🗡️",
		"fishname": "dagger",
		"catchtype": "normal",
		"chat": "d_egree",
		"fishid": 100336,
		"chatid": 42,
		"date": "2024-09-09T15:45:49Z",
		"rank": 22
	},
	"darksunglasses": {
		"player": "larvasisters",
		"playerid": 1212,
		"weight": 12.16,
		"bot": "gofishgame",
		"fishtype": "🕶️",
		"fishname": "darksunglasses",
		"catchtype": "normal",
		"chat": "d_egree",
		"fishid": 82423,
		"chatid": 6,
		"date": "2024-06-05T20:25:47Z",
		"rank": 23
	},
	"dolphin": {
		"player": "kohrro",
		"playerid": 2887,
		"weight": 72.65,
		"bot": "gofishgame",
		"fishtype": "🐬",
		"fishname": "dolphin",
		"catchtype": "normal",
		"chat": "d_egree",
		"fishid": 102547,
		"chatid": 90,
		"date": "2024-09-21T23:24:30Z",
		"rank": 11
	},
	"dragon": {
		"player": "benni900",
		"playerid": 228,
		"weight": 173.1,
		"bot": "gofishgame",
		"fishtype": "🐉",
		"fishname": "dragon",
		"catchtype": "normal",
		"chat": "d_egree",
		"fishid": 149676,
		"chatid": 245,
		"date": "2025-02-24T09:14:48Z",
		"rank": 1
	},
	"duck": {
		"player": "kohrro",
		"playerid": 2887,
		"weight": 10.39,
		"bot": "gofishgame",
		"fishtype": "🦆",
		"fishname": "duck",
		"catchtype": "normal",
		"chat": "d_egree",
		"fishid": 99244,
		"chatid": 24,
		"date": "2024-09-03T14:58:44Z",
		"rank": 24
	},
	"fish": {
		"player": "kohrro",
		"playerid": 2887,
		"weight": 40.87,
		"bot": "gofishgame",
		"fishtype": "🐟",
		"fishname": "fish",
		"catchtype": "normal",
		"chat": "d_egree",
		"fishid": 105318,
		"chatid": 136,
		"date": "2024-10-01T01:30:58Z",
		"rank": 15
	},
	"frog": {
		"player": "kohrro",
		"playerid": 2887,
		"weight": 4.72,
		"bot": "gofishgame",
		"fishtype": "🐸",
		"fishname": "frog",
		"catchtype": "normal",
		"chat": "d_egree",
		"fishid": 102623,
		"chatid": 91,
		"date": "2024-09-22T11:51:06Z",
		"rank": 33
	},
	"gloves": {
		"player": "benni900",
		"playerid": 228,
		"weight": 0.7,
		"bot": "gofishgame",
		"fishtype": "🧤",
		"fishname": "gloves",
		"catchtype": "normal",
		"chat": "d_egree",
		"fishid": 147984,
		"chatid": 183,
		"date": "2025-02-15T22:44:26Z",
		"rank": 54
	},
	"hook": {
		"player": "larvasisters",
		"playerid": 1212,
		"weight": 3.95,
		"bot": "gofishgame",
		"fishtype": "🪝",
		"fishname": "hook",
		"catchtype": "normal",
		"chat": "d_egree",
		"fishid": 82290,
		"chatid": 5,
		"date": "2024-06-05T00:49:25Z",
		"rank": 37
	},
	"icecube": {
		"player": "benni900",
		"playerid": 228,
		"weight": 6.66,
		"bot": "gofishgame",
		"fishtype": "🧊",
		"fishname": "icecube",
		"catchtype": "normal",
		"chat": "d_egree",
		"fishid": 149241,
		"chatid": 230,
		"date": "2025-02-21T16:16:42Z",
		"rank": 31
	},
	"iphone": {
		"player": "kohrro",
		"playerid": 2887,
		"weight": 7.64,
		"bot": "gofishgame",
		"fishtype": "📱",
		"fishname": "iphone",
		"catchtype": "normal",
		"chat": "d_egree",
		"fishid": 154440,
		"chatid": 258,
		"date": "2025-03-13T12:07:24Z",
		"rank": 28
	},
	"jar": {
		"player": "kohrro",
		"playerid": 2887,
		"weight": 0.95,
		"bot": "gofishgame",
		"fishtype": "🫙",
		"fishname": "jar",
		"catchtype": "normal",
		"chat": "d_egree",
		"fishid": 196309,
		"chatid": 303,
		"date": "2025-08-30T14:10:11Z",
		"rank": 51
	},
	"ladybug": {
		"player": "kohrro",
		"playerid": 2887,
		"weight": 0.36,
		"bot": "gofishgame",
		"fishtype": "🐞",
		"fishname": "ladybug",
		"catchtype": "normal",
		"chat": "d_egree",
		"fishid": 196296,
		"chatid": 302,
		"date": "2025-08-30T13:10:00Z",
		"rank": 56
	},
	"leaf": {
		"player": "kohrro",
		"playerid": 2887,
		"weight": 1.38,
		"bot": "gofishgame",
		"fishtype": "🍃",
		"fishname": "leaf",
		"catchtype": "normal",
		"chat": "d_egree",
		"fishid": 179268,
		"chatid": 281,
		"date": "2025-06-13T12:43:36Z",
		"rank": 48
	},
	"lizard": {
		"player": "kohrro",
		"playerid": 2887,
		"weight": 7.47,
		"bot": "gofishgame",
		"fishtype": "🦎",
		"fishname": "lizard",
		"catchtype": "normal",
		"chat": "d_egree",
		"fishid": 181968,
		"chatid": 298,
		"date": "2025-06-24T09:22:24Z",
		"rank": 29
	},
	"lobster": {
		"player": "benni900",
		"playerid": 228,
		"weight": 41.43,
		"bot": "gofishgame",
		"fishtype": "🦞",
		"fishname": "lobster",
		"catchtype": "normal",
		"chat": "d_egree",
		"fishid": 148582,
		"chatid": 210,
		"date": "2025-02-18T14:04:40Z",
		"rank": 14
	},
	"log": {
		"player": "kohrro",
		"playerid": 2887,
		"weight": 4.69,
		"bot": "gofishgame",
		"fishtype": "🪵",
		"fishname": "log",
		"catchtype": "normal",
		"chat": "d_egree",
		"fishid": 110382,
		"chatid": 152,
		"date": "2024-10-18T00:03:02Z",
		"rank": 34
	},
	"lure": {
		"player": "riki482",
		"playerid": 3575,
		"weight": 4.29,
		"bot": "gofishgame",
		"fishtype": "🎏",
		"fishname": "lure",
		"catchtype": "normal",
		"chat": "d_egree",
		"fishid": 148865,
		"chatid": 220,
		"date": "2025-02-19T19:48:40Z",
		"rank": 35
	},
	"mapleleaf": {
		"player": "kohrro",
		"playerid": 2887,
		"weight": 0.56,
		"bot": "gofishgame",
		"fishtype": "🍁",
		"fishname": "mapleleaf",
		"catchtype": "normal",
		"chat": "d_egree",
		"fishid": 105291,
		"chatid": 133,
		"date": "2024-09-30T23:22:41Z",
		"rank": 55
	},
	"mushroom": {
		"player": "benni900",
		"playerid": 228,
		"weight": 2.62,
		"bot": "gofishgame",
		"fishtype": "🍄",
		"fishname": "mushroom",
		"catchtype": "normal",
		"chat": "d_egree",
		"fishid": 149732,
		"chatid": 250,
		"date": "2025-02-24T15:10:12Z",
		"rank": 41
	},
	"nestwitheggs": {
		"player": "kohrro",
		"playerid": 2887,
		"weight": 2.6,
		"bot": "gofishgame",
		"fishtype": "🪺",
		"fishname": "nestwitheggs",
		"catchtype": "normal",
		"chat": "d_egree",
		"fishid": 103768,
		"chatid": 97,
		"date": "2024-09-26T16:56:22Z",
		"rank": 42
	},
	"octopus": {
		"player": "kohrro",
		"playerid": 2887,
		"weight": 97.11,
		"bot": "gofishgame",
		"fishtype": "🐙",
		"fishname": "octopus",
		"catchtype": "normal",
		"chat": "d_egree",
		"fishid": 101633,
		"chatid": 61,
		"date": "2024-09-16T11:00:23Z",
		"rank": 7
	},
	"oyster": {
		"player": "kohrro",
		"playerid": 2887,
		"weight": 27.65,
		"bot": "gofishgame",
		"fishtype": "🦪",
		"fishname": "oyster",
		"catchtype": "normal",
		"chat": "d_egree",
		"fishid": 138767,
		"chatid": 172,
		"date": "2025-01-04T19:30:07Z",
		"rank": 16
	},
	"plankton": {
		"player": "benni900",
		"playerid": 228,
		"weight": 21.65,
		"bot": "gofishgame",
		"fishtype": "🦠",
		"fishname": "plankton",
		"catchtype": "normal",
		"chat": "d_egree",
		"fishid": 148350,
		"chatid": 201,
		"date": "2025-02-17T11:38:32Z",
		"rank": 18
	},
	"sauropod": {
		"player": "benni900",
		"playerid": 228,
		"weight": 125.87,
		"bot": "gofishgame",
		"fishtype": "🦕",
		"fishname": "sauropod",
		"catchtype": "normal",
		"chat": "d_egree",
		"fishid": 148838,
		"chatid": 218,
		"date": "2025-02-19T17:48:07Z",
		"rank": 4
	},
	"seal": {
		"player": "benni900",
		"playerid": 228,
		"weight": 123.31,
		"bot": "gofishgame",
		"fishtype": "🦭",
		"fishname": "seal",
		"catchtype": "normal",
		"chat": "d_egree",
		"fishid": 148855,
		"chatid": 219,
		"date": "2025-02-19T18:50:23Z",
		"rank": 5
	},
	"seaweed": {
		"player": "larvasisters",
		"playerid": 1212,
		"weight": 0.78,
		"bot": "gofishgame",
		"fishtype": "🌿",
		"fishname": "seaweed",
		"catchtype": "normal",
		"chat": "d_egree",
		"fishid": 81746,
		"chatid": 2,
		"date": "2024-06-01T20:46:09Z",
		"rank": 53
	},
	"shamrock": {
		"player": "kohrro",
		"playerid": 2887,
		"weight": 1.65,
		"bot": "gofishgame",
		"fishtype": "☘️",
		"fishname": "shamrock",
		"catchtype": "normal",
		"chat": "d_egree",
		"fishid": 104925,
		"chatid": 129,
		"date": "2024-09-29T21:59:37Z",
		"rank": 45
	},
	"shark": {
		"player": "benni900",
		"playerid": 228,
		"weight": 129.36,
		"bot": "gofishgame",
		"fishtype": "🦈",
		"fishname": "shark",
		"catchtype": "normal",
		"chat": "d_egree",
		"fishid": 147916,
		"chatid": 174,
		"date": "2025-02-15T17:05:41Z",
		"rank": 3
	},
	"shell": {
		"player": "mitgliederversammlung",
		"playerid": 17,
		"verified": true,
		"weight": 3.65,
		"bot": "gofishgame",
		"fishtype": "🐚",
		"fishname": "shell",
		"catchtype": "normal",
		"chat": "d_egree",
		"fishid": 87801,
		"chatid": 9,
		"date": "2024-07-03T15:10:00Z",
		"rank": 38
	},
	"shrimp": {
		"player": "benni900",
		"playerid": 228,
		"weight": 21.19,
		"bot": "gofishgame",
		"fishtype": "🦐",
		"fishname": "shrimp",
		"catchtype": "normal",
		"chat": "d_egree",
		"fishid": 148385,
		"chatid": 205,
		"date": "2025-02-17T15:31:00Z",
		"rank": 19
	},
	"skull": {
		"player": "kohrro",
		"playerid": 2887,
		"weight": 8.96,
		"bot": "gofishgame",
		"fishtype": "💀",
		"fishname": "skull",
		"catchtype": "normal",
		"chat": "d_egree",
		"fishid": 99047,
		"chatid": 11,
		"date": "2024-09-02T16:31:59Z",
		"rank": 25
	},
	"snail": {
		"player": "kohrro",
		"playerid": 2887,
		"weight": 1.26,
		"bot": "gofishgame",
		"fishtype": "🐌",
		"fishname": "snail",
		"catchtype": "normal",
		"chat": "d_egree",
		"fishid": 99085,
		"chatid": 16,
		"date": "2024-09-02T19:55:10Z",
		"rank": 49
	},
	"snake": {
		"player": "kohrro",
		"playerid": 2887,
		"weight": 58.59,
		"bot": "gofishgame",
		"fishtype": "🐍",
		"fishname": "snake",
		"catchtype": "normal",
		"chat": "d_egree",
		"fishid": 135367,
		"chatid": 161,
		"date": "2024-12-25T19:02:58Z",
		"rank": 12
	},
	"socks": {
		"player": "kohrro",
		"playerid": 2887,
		"weight": 1.82,
		"bot": "gofishgame",
		"fishtype": "🧦",
		"fishname": "socks",
		"catchtype": "normal",
		"chat": "d_egree",
		"fishid": 101118,
		"chatid": 49,
		"date": "2024-09-13T16:35:45Z",
		"rank": 44
	},
	"spider": {
		"player": "benni900",
		"playerid": 228,
		"weight": 8.24,
		"bot": "gofishgame",
		"fishtype": "🕷️",
		"fishname": "spider",
		"catchtype": "normal",
		"chat": "d_egree",
		"fishid": 149294,
		"chatid": 231,
		"date": "2025-02-22T00:07:51Z",
		"rank": 27
	},
	"squid": {
		"player": "kohrro",
		"playerid": 2887,
		"weight": 78.9,
		"bot": "gofishgame",
		"fishtype": "🦑",
		"fishname": "squid",
		"catchtype": "normal",
		"chat": "d_egree",
		"fishid": 100908,
		"chatid": 47,
		"date": "2024-09-12T16:11:09Z",
		"rank": 10
	},
	"thongsandal": {
		"player": "kohrro",
		"playerid": 2887,
		"weight": 1.63,
		"bot": "gofishgame",
		"fishtype": "🩴",
		"fishname": "thongsandal",
		"catchtype": "normal",
		"chat": "d_egree",
		"fishid": 101722,
		"chatid": 63,
		"date": "2024-09-16T19:47:21Z",
		"rank": 46
	},
	"tropicalfish": {
		"player": "shpeelerin",
		"playerid": 100,
		"weight": 19.31,
		"bot": "supibot",
		"fishtype": "🐠",
		"fishname": "tropicalfish",
		"catchtype": "normal",
		"chat": "d_egree",
		"fishid": 163732,
		"chatid": 268,
		"date": "2023-09-11T14:04:53Z",
		"rank": 21
	},
	"turtle": {
		"player": "kohrro",
		"playerid": 2887,
		"weight": 89.56,
		"bot": "gofishgame",
		"fishtype": "🐢",
		"fishname": "turtle",
		"catchtype": "normal",
		"chat": "d_egree",
		"fishid": 105210,
		"chatid": 131,
		"date": "2024-09-30T17:53:24Z",
		"rank": 9
	},
	"umbrella": {
		"player": "benni900",
		"playerid": 228,
		"weight": 2.19,
		"bot": "gofishgame",
		"fishtype": "☂️",
		"fishname": "umbrella",
		"catchtype": "normal",
		"chat": "d_egree",
		"fishid": 147942,
		"chatid": 177,
		"date": "2025-02-15T18:47:16Z",
		"rank": 43
	},
	"whale": {
		"player": "kohrro",
		"playerid": 2887,
		"weight": 96.95,
		"bot": "gofishgame",
		"fishtype": "🐳",
		"fishname": "whale",
		"catchtype": "normal",
		"chat": "d_egree",
		"fishid": 137432,
		"chatid": 169,
		"date": "2024-12-31T15:55:23Z",
		"rank": 8
	},
	"whale2": {
		"player": "benni900",
		"playerid": 228,
		"weight": 109.58,
		"bot": "gofishgame",
		"fishtype": "🐋",
		"fishname": "whale2",
		"catchtype": "normal",
		"chat": "d_egree",
		"fishid": 160348,
		"chatid": 264,
		"date": "2025-03-30T11:19:45Z",
		"rank": 6
	},
	"wireline": {
		"player": "kohrro",
		"playerid": 2887,
		"weight": 0.01,
		"bot": "gofishgame",
		"fishtype": "🧵",
		"fishname": "wireline",
		"catchtype": "normal",
		"chat": "d_egree",
		"fishid": 181211,
		"chatid": 288,
		"date": "2025-06-22T20:28:56Z",
		"rank": 59
	}
}